wifipasswords/__init__.py
wifipasswords/__main__.py
wifipasswords/wifipasswords_linux.py
wifipasswords/wifipasswords_macos.py
wifipasswords/wifipasswords_windows.py
wifipasswords-0.4.1b0.dist-info/LICENCE
wifipasswords-0.4.1b0.dist-info/METADATA
wifipasswords-0.4.1b0.dist-info/WHEEL
wifipasswords-0.4.1b0.dist-info/entry_points.txt
wifipasswords-0.4.1b0.dist-info/top_level.txt
wifipasswords-0.4.1b0.dist-info/RECORD
