Metadata-Version: 2.1
Name: wifipasswords
Version: 0.4.1-beta-
Summary: Retrieve and save all WiFi networks and passwords on the device. Cross platform windows, linux, macOS
Home-page: https://github.com/needs-coffee/wifipasswords
Author: Joe Campbell
License: GPLv3
Project-URL: Bug Tracker, https://github.com/needs-coffee/wifipasswords/issues
Keywords: wifipasswords,passwords,wifi,networks,dns,wpasupplicant
Classifier: Development Status :: 4 - Beta
Classifier: Programming Language :: Python :: 3
Classifier: License :: OSI Approved :: GNU General Public License v3 (GPLv3)
Classifier: Operating System :: OS Independent
Classifier: Natural Language :: English
Classifier: Topic :: Utilities
Classifier: Topic :: System :: Systems Administration
Classifier: Topic :: System :: Networking
Requires-Python: >=3.6
License-File: LICENCE
Requires-Dist: colorama (>=0.4.4)
